frequently/__init__.py
frequently/admin.py
frequently/cms_app.py
frequently/forms.py
frequently/models.py
frequently/urls.py
frequently/views.py
frequently/migrations/0001_initial.py
frequently/migrations/0002_auto_20150911_1153.py
frequently/migrations/0003_auto_20181220_0941.py
frequently/migrations/__init__.py
frequently/south_migrations/0001_initial.py
frequently/south_migrations/__init__.py
frequently/static/frequently/js/frequently.js
frequently/templates/frequently/entry_form.html
frequently/templates/frequently/entry_list.html
frequently/templates/frequently/plugin.html
frequently/templates/frequently/email/new_question_body.txt
frequently/templates/frequently/email/new_question_subject.txt
frequently/templates/frequently/partials/answer.html
frequently/templates/frequently/partials/category.html
frequently/templates/frequently/partials/entry.html
frequently/templates/frequently/partials/feedback.html
frequently/templates/frequently/partials/feedback_form.html
frequently/templatetags/__init__.py
frequently/templatetags/frequently_tags.py
frequently/tests/__init__.py
frequently/tests/forms_tests.py
frequently/tests/models_tests.py
frequently/tests/settings.py
frequently/tests/tags_tests.py
frequently/tests/test_settings.py
frequently/tests/urls.py
frequently/tests/views_tests.py
frequently/tests/test_app/__init__.py
frequently/tests/test_app/models.py
frequently/tests/test_app/templates/404.html
frequently/tests/test_app/templates/500.html
frequently/tests/test_app/templates/base.html
frequently/tests/test_app/templates/tag_test.html
django_frequently-2.0.0.dist-info/AUTHORS
django_frequently-2.0.0.dist-info/LICENSE
django_frequently-2.0.0.dist-info/METADATA
django_frequently-2.0.0.dist-info/WHEEL
django_frequently-2.0.0.dist-info/top_level.txt
django_frequently-2.0.0.dist-info/RECORD
