Metadata-Version: 2.1
Name: django-frequently
Version: 2.0.0
Summary: A reusable Django app that can be used as a FAQ.
Requires-Dist: Django
Requires-Dist: django-libs
Requires-Dist: django-ckeditor
